docbase.py
docbase_client-0.1.0.dist-info/DESCRIPTION.rst
docbase_client-0.1.0.dist-info/METADATA
docbase_client-0.1.0.dist-info/RECORD
docbase_client-0.1.0.dist-info/WHEEL
docbase_client-0.1.0.dist-info/metadata.json
docbase_client-0.1.0.dist-info/top_level.txt
