Metadata-Version: 2.0
Name: docbase-client
Version: 0.1.0
Summary: Python client for DocBase API.
Home-page: https://github.com/kit494way/docbase-python-client
Author: KITAGAWA Yasutaka
Author-email: kit494way@gmail.com
License: MIT
Keywords: docbase api client
Platform: UNKNOWN
Classifier: Development Status :: 4 - Beta
Classifier: Intended Audience :: Developers
Classifier: Topic :: Software Development
Classifier: License :: OSI Approved :: MIT License
Classifier: Programming Language :: Python :: 3.5
Classifier: Programming Language :: Python :: 3.6
Requires-Python: ~=3.5
Requires-Dist: requests
